biencrypt_lib.py
biencrypt-1.0.0.dist-info/licenses/LICENSE
biencrypt-1.0.0.dist-info/METADATA
biencrypt-1.0.0.dist-info/WHEEL
biencrypt-1.0.0.dist-info/top_level.txt
biencrypt-1.0.0.dist-info/RECORD
